setup.py
WinMicro/__init__.py
WinMicro.egg-info/PKG-INFO
WinMicro.egg-info/SOURCES.txt
WinMicro.egg-info/dependency_links.txt
WinMicro.egg-info/top_level.txt